{
    "page": 3,
    "results": [
        {
            "adult": false,
            "backdrop_path": "/94kQGMiFbs5MUTlt7kj9dewsMDi.jpg",
            "genre_ids": [
                27,
                53
            ],
            "id": 676547,
            "original_language": "en",
            "original_title": "Prey for the Devil",
            "overview": "과거의 트라우마로 여전히 고통 받고 있는 수녀 앤  구마 의식 학교에서 특별한 재능을 인정받으며 남성 사제에게만 허용되었던 구마 의식 훈련을 받게 되고  그곳에서 만난 환자들을 통해 어릴 적부터 그녀를 괴롭혀 왔던 존재의 실체와 만나게 되는데...",
            "popularity": 408.692,
            "poster_path": "/zNFUrnycnAFp7xukctFg1Ey7YBH.jpg",
            "release_date": "2022-10-23",
            "title": "프레이 포 더 데블",
            "video": false,
            "vote_average": 7.2,
            "vote_count": 553
        },
        {
            "adult": false,
            "backdrop_path": "/AaV1YIdWKnjAIAOe8UUKBFm327v.jpg",
            "genre_ids": [
                28,
                18
            ],
            "id": 361743,
            "original_language": "en",
            "original_title": "Top Gun: Maverick",
            "overview": "최고의 파일럿이자 전설적인 인물 매버릭은 자신이 졸업한 훈련학교 교관으로 발탁된다. 그의 명성을 모르던 팀원들은 매버릭의 지시를 무시하지만 실전을 방불케 하는 상공 훈련에서 눈으로 봐도 믿기 힘든 전설적인 조종 실력에 모두가 압도된다. 매버릭의 지휘 아래 견고한 팀워크를 쌓아가던 팀원들에게 국경을 뛰어넘는 위험한 임무가 주어지자 매버릭은 자신이 가르친 동료들과 함께 마지막이 될지 모를 하늘 위 비행에 나서는데...",
            "popularity": 372.899,
            "poster_path": "/jeqXUwNilvNqNXqAHsdwm5pEfae.jpg",
            "release_date": "2022-05-24",
            "title": "탑건: 매버릭",
            "video": false,
            "vote_average": 8.3,
            "vote_count": 6334
        },
        {
            "adult": false,
            "backdrop_path": "/jsoz1HlxczSuTx0mDl2h0lxy36l.jpg",
            "genre_ids": [
                14,
                28,
                35
            ],
            "id": 616037,
            "original_language": "en",
            "original_title": "Thor: Love and Thunder",
            "overview": "이너피스를 위해 자아 찾기 여정을 떠난 천둥의 신 토르. 그러나 우주의 모든 신들을 몰살하려는 신 도살자 고르의 등장으로 토르의 안식년 계획은 산산조각 나 버린다. 토르는새로운 위협에 맞서기 위해 킹 발키리, 코르그, 그리고 전 여자친구 제인과 재회하게 되고, 그녀가 묠니르를 휘두르는 마이티 토르가 되어 나타나 모두를 놀라게 한다. 이제 팀 토르는 고르의 복수에 얽힌 미스터리를 밝히고 더 큰 전쟁을 막기 위한 전 우주적 스케일의 모험을 시작하는데...",
            "popularity": 398.62,
            "poster_path": "/un8ZDtx2SMwNwXRYy65aItnNjab.jpg",
            "release_date": "2022-07-06",
            "title": "토르: 러브 앤 썬더",
            "video": false,
            "vote_average": 6.6,
            "vote_count": 5568
        },
        {
            "adult": false,
            "backdrop_path": "/2E6pIbJien7B9yWpaz8Yd2njzUI.jpg",
            "genre_ids": [
                18,
                27
            ],
            "id": 1026563,
            "original_language": "es",
            "original_title": "13 exorcismos",
            "overview": "",
            "popularity": 579.225,
            "poster_path": "/2yzpiUeOQHnbiOayAAwG0FcXRmc.jpg",
            "release_date": "2022-11-04",
            "title": "13 exorcismos",
            "video": false,
            "vote_average": 6.4,
            "vote_count": 8
        },
        {
            "adult": false,
            "backdrop_path": "/9j0V8Fw5u4cv9cESUXUmTGmpXU5.jpg",
            "genre_ids": [
                16,
                10751,
                35
            ],
            "id": 1058732,
            "original_language": "en",
            "original_title": "The Simpsons Meet the Bocellis in Feliz Navidad",
            "overview": "",
            "popularity": 375.941,
            "poster_path": "/9rJFKvYvSyQ3HoTl1gcU55FOzYi.jpg",
            "release_date": "2022-12-15",
            "title": "The Simpsons Meet the Bocellis in Feliz Navidad",
            "video": false,
            "vote_average": 5.2,
            "vote_count": 30
        },
        {
            "adult": false,
            "backdrop_path": "/5pMy5LF2JAleBNBtuzizfCMWM7k.jpg",
            "genre_ids": [
                10752,
                36,
                18
            ],
            "id": 653851,
            "original_language": "en",
            "original_title": "Devotion",
            "overview": "미 해군 최초의 흑인 파일럿 제시 브라운. 한국 전쟁에서 위험을 무릅쓴 비행에 나선다. 그리고 그의 곁에는 생사를 함께하는 윙맨 톰 허드너가 있다.",
            "popularity": 381.034,
            "poster_path": "/lwybGlEEJtXZM3ynY19PNwNlPn9.jpg",
            "release_date": "2022-11-23",
            "title": "디보션",
            "video": false,
            "vote_average": 7.4,
            "vote_count": 368
        },
        {
            "adult": false,
            "backdrop_path": "/tsjXBo4LmzV0Bb9hdrz25tzX5GD.jpg",
            "genre_ids": [
                10402
            ],
            "id": 1041513,
            "original_language": "en",
            "original_title": "Encanto at the Hollywood Bowl",
            "overview": "월트 디즈니 애니메이션 스튜디오의 '엔칸토 할리우드 볼'의 성우가 카사 마드리갈로 돌아온다.  스테파니 베아트리스, 어대사, 캐롤라이나 가이탄, 제시카 대로, 다이앤 게레로, 마우로 카스티요, 앤지 세페다, 올가 메레다이즈가 콜롬비아의 카를로스 비베스 등의 특별 게스트와 출연하는 이 라이브를 영화화한 콘서트는 '엔칸토 할리우드 볼'의 세계, 캐릭터, 노래를 기념한다.",
            "popularity": 367.39,
            "poster_path": "/sa3Ku5yNVjp8NloWxJoI9dQjvOi.jpg",
            "release_date": "2022-12-28",
            "title": "엔칸토 할리우드 볼",
            "video": false,
            "vote_average": 7.3,
            "vote_count": 106
        },
        {
            "adult": false,
            "backdrop_path": "/4B6bYj7gr5wQBvQQhDwr6tzJyGR.jpg",
            "genre_ids": [
                10752,
                18
            ],
            "id": 966220,
            "original_language": "uk",
            "original_title": "Снайпер. Білий ворон",
            "overview": "미콜라는 친환경적인 삶을 살기 위해 아내와 시골로 내려와 물리 교사를 하며 지내던 중, 러시아 무장 단체의 공격을 받아 임신한 아내가 사망하게 된다. 쓰러진 미콜라를 발견한 우크라이나 군은 군대에 미콜라를 데려가고, 분노에 찬 미콜라는 복수를 위해 저격수가 될 결심을 하는데…",
            "popularity": 367.144,
            "poster_path": "/66mrr3AK6grmkfGJ1wlCP8dkzjM.jpg",
            "release_date": "2022-05-03",
            "title": "스나이퍼: 화이트 레이븐",
            "video": false,
            "vote_average": 7.6,
            "vote_count": 327
        },
        {
            "adult": false,
            "backdrop_path": "/8H2O044M0xp240emFWAXjZsfLLx.jpg",
            "genre_ids": [
                53,
                878,
                28
            ],
            "id": 700391,
            "original_language": "en",
            "original_title": "65",
            "overview": "",
            "popularity": 375.438,
            "poster_path": "/uMMIeMVk1TCG3CZilpxbzFh0JKT.jpg",
            "release_date": "2023-03-02",
            "title": "65",
            "video": false,
            "vote_average": 5.9,
            "vote_count": 58
        },
        {
            "adult": false,
            "backdrop_path": "/e8BCc8Jk11dnSffI6ElICLePvLZ.jpg",
            "genre_ids": [
                28,
                53,
                80
            ],
            "id": 603692,
            "original_language": "en",
            "original_title": "John Wick: Chapter 4",
            "overview": "존 윅은 자신의 목숨값이 점점 올라가는 상황에서 '하이 테이블'을 물리칠 수 있는 길을 찾아낸다. 하지만 자유를 얻기 전에 존 윅은 전 세계의 강력한 동맹과 오랜 친구를 적으로 돌리는 세력을 가진 새로운 적과 맞서 싸워야 하는데...",
            "popularity": 392.037,
            "poster_path": "/1HNnCwkidcUtfpcrW9TGwj7Ypiz.jpg",
            "release_date": "2023-03-22",
            "title": "존 윅 4",
            "video": false,
            "vote_average": 9.2,
            "vote_count": 6
        },
        {
            "adult": false,
            "backdrop_path": "/t1XwJqQNH6CPgkG2vU5i82U12Tt.jpg",
            "genre_ids": [
                18,
                10749
            ],
            "id": 554447,
            "original_language": "ko",
            "original_title": "여직원의 맛",
            "overview": "*여직원의 맛*  박과장은 사무실에서 호시탐탐 여직원 가희를 두고 혼자만의 상상을 하는데 이런 박과장의 시선이 너무 부담스러운 가희, 어느날 박과장이 먼저 퇴근하고 비밀연애를 하는 직장동료 우진과 사무실에서 섹스를 즐긴다. 잠시후 퇴근한 박과장이 문을 여는데...  *극장의 맛1*  극장에서 영화를 보고있는 연인, 영호와 수련은 주변에 사람이 없자 수련에게 들이대는 영호, 뒤에 사람이 있다며 영호를 말린다. 잠시후 화장실에 갔다온 수련은 안경이 부서져서 앞을 잘 못보고 영호가 아닌, 낯선 남자 옆으로 가는데...  *모텔의 맛*  학교선후배 영호와 혜진이 모텔에서 맥주를 마신다. 혜진이 조만간 남자친구와 첫날밤을 치룰 것이라며, 예행연습을 하자고 후배한테 제안한다. 영호는 걱정말라며 호기롭게 이야기 하지만, 이내 혜진의 첫경험이 처음이 아닌 것을 느낀다.  *극장의 맛2*  시련의 상처로 혼자 영화보고 있는 영호 옆으로 낯선 여자 수련이 앉는다.영호의 사연을 우연히 듣게 되고, 영호를 위로하던 중 조용한 극장에서 둘만의 섹스를 즐긴다.",
            "popularity": 374.865,
            "poster_path": "/sf5l6ZsSgzgxZ3IicFfkOXp8AZy.jpg",
            "release_date": "2018-05-28",
            "title": "여직원의 맛",
            "video": false,
            "vote_average": 4.7,
            "vote_count": 26
        },
        {
            "adult": false,
            "backdrop_path": "/9iRRfMZbnpgHDdKi2lczGGYZXDo.jpg",
            "genre_ids": [
                12,
                10751,
                14
            ],
            "id": 411,
            "original_language": "en",
            "original_title": "The Chronicles of Narnia: The Lion, the Witch and the Wardrobe",
            "overview": "제2차 세계대전 중의 영국. 공습을 피해 디고리 교수의 시골 별장으로 간 페번시가의 네 남매인 피터, 수잔, 에드먼드, 루시는 마법의 옷장을 통해 신비로운 나라 나니아로 들어선다. 말하는 동물들과 켄타우로스, 거인들이 평화롭게 어울려 사는 땅이었던 나니아는 사악한 하얀 마녀 제이디스에 의해 긴 겨울에 감금되어 있다. 게다가 이 겨울에는 크리스마스도 없다. 호기심 많은 루시, 퉁명스러운 에드먼드, 신중한 수잔, 분별 있는 맏이 피터는 고귀한 사자 아슬란의 인도로 제이디스의 싸늘한 주문을 깨는 싸움에 가담한다.",
            "popularity": 384.078,
            "poster_path": "/vSY6MgDWD5Ch5I87X8BaxZyydCI.jpg",
            "release_date": "2005-12-07",
            "title": "나니아 연대기: 사자, 마녀 그리고 옷장",
            "video": false,
            "vote_average": 7.1,
            "vote_count": 9398
        },
        {
            "adult": false,
            "backdrop_path": "/dOGgJb7eDW623UzeBaSjPwq5EJO.jpg",
            "genre_ids": [
                18
            ],
            "id": 840789,
            "original_language": "es",
            "original_title": "Matadero",
            "overview": "",
            "popularity": 365.702,
            "poster_path": "/8YHXvW1GWEcXAZXXSHfTsaGi4i2.jpg",
            "release_date": "2022-12-09",
            "title": "Matadero",
            "video": false,
            "vote_average": 3,
            "vote_count": 1
        },
        {
            "adult": false,
            "backdrop_path": "/Aqldsq65Nj1KAkQD2MzkZsAk5N5.jpg",
            "genre_ids": [
                28,
                53,
                18
            ],
            "id": 846433,
            "original_language": "es",
            "original_title": "The Enforcer",
            "overview": "",
            "popularity": 374.452,
            "poster_path": "/5bRvU3t24rUOd99CIGjeSXc6vDX.jpg",
            "release_date": "2022-09-22",
            "title": "인포서",
            "video": false,
            "vote_average": 7.3,
            "vote_count": 265
        },
        {
            "adult": false,
            "backdrop_path": "/vXjpwkXPirBmgdEpIknfN8ziDD.jpg",
            "genre_ids": [
                16,
                12,
                14,
                35
            ],
            "id": 947938,
            "original_language": "ru",
            "original_title": "Мальчик-дельфин",
            "overview": "돌고래야, 사람이야?! 정체를 알 수 없는 녀석이 온다! 바다 속 돌고래와 함께 자란 소년 ‘보이’ 어느 날 친엄마의 존재를 알게 된 ‘보이’는 자신의 뿌리를 궁금해하기 시작하고 … 혼란스러운 상황 속 ‘보이’는 악당 ‘옥토퍼스’로 인해 엄마 돌고래 ‘나나’를 잃고 해안가로 떠밀려간다. 평생을 자신이 돌고래인 줄 알고 살던 ‘보이’는 해안가에 사는 ‘머버리드 선장’의 도움으로 친엄마를 찾아내기로 결심하는데 … 2023년, 올겨울 유일무이 오션 어드벤처가 온다!",
            "popularity": 363.146,
            "poster_path": "/Aif2IsFGCur5KoXnjkXyAhishMj.jpg",
            "release_date": "2022-04-07",
            "title": "돌핀보이",
            "video": false,
            "vote_average": 6.5,
            "vote_count": 45
        },
        {
            "adult": false,
            "backdrop_path": "/8NEvnVKeGMLEXG45MMNqxJLcM4y.jpg",
            "genre_ids": [
                28,
                16,
                14
            ],
            "id": 820232,
            "original_language": "ja",
            "original_title": "鬼滅の刃 兄妹の絆",
            "overview": "혈귀의 습격으로 가족을 잃은 소년 ‘탄지로’. 유일하게 살아남은 여동생 ‘네즈코’마저 혈귀로 변해 버리고 마는데…. ‘탄지로’는 ‘네즈코’를 인간으로 되돌리기 위해- 그리고 가족을 죽인 혈귀를 심판하기 위해- ‘귀살대’의 길을 가기로 결의한다. 혹독한 훈련 끝에 귀살대 대원으로 거듭난 ‘탄지로’는 복수의 칼날을 들고 목숨 건 사투를 시작하는데… 소년이여, 여동생을 구하기 위해 칼날을 들어라! 인간과 혈귀가 엮어낸 애절한 오누이의 이야기가 지금 시작된다-!",
            "popularity": 347.47,
            "poster_path": "/3vlBg3kTsHioTy7owIDXFHNXBNk.jpg",
            "release_date": "2019-03-29",
            "title": "귀멸의 칼날: 남매의 연",
            "video": false,
            "vote_average": 8,
            "vote_count": 71
        },
        {
            "adult": false,
            "backdrop_path": "/14QbnygCuTO0vl7CAFmPf1fgZfV.jpg",
            "genre_ids": [
                28,
                12,
                878
            ],
            "id": 634649,
            "original_language": "en",
            "original_title": "Spider-Man: No Way Home",
            "overview": "미스테리오의 계략으로 세상에 정체가 탄로난 스파이더맨 피터 파커는 하루 아침에 평범한 일상을 잃게 된다. 문제를 해결하기 위해 닥터 스트레인지를 찾아가 도움을 청하지만 뜻하지 않게 멀티버스가 열리면서 각기 다른 차원의 불청객들이 나타난다. 닥터 옥토퍼스를 비롯해 스파이더맨에게 깊은 원한을 가진 숙적들의 강력한 공격에 피터 파커는 사상 최악의 위기를 맞게 되는데…",
            "popularity": 365.471,
            "poster_path": "/voddFVdjUoAtfoZZp2RUmuZILDI.jpg",
            "release_date": "2021-12-15",
            "title": "스파이더맨: 노 웨이 홈",
            "video": false,
            "vote_average": 8,
            "vote_count": 16961
        },
        {
            "adult": false,
            "backdrop_path": "/nWs0auTqn2UaFGfTKtUE5tlTeBu.jpg",
            "genre_ids": [
                10751,
                35,
                14
            ],
            "id": 668482,
            "original_language": "en",
            "original_title": "Roald Dahl's Matilda the Musical",
            "overview": "남다른 소녀가 나타났다.  명석한 두뇌와 풍부한 상상력으로 무장한 소녀의 이야기.  이 특별한 아이는 자신의 이야기를 기적적인 결과로 바꾸고자 당당하게 나선다.  토니상 및 올리비에상 수상 뮤지컬을 새롭게 각색한 '로알드 달의 뮤지컬 마틸다'.  놀라운 상상력을 가진 특별한 소녀가 용기를 발휘해 운명을 개척하고 기적 같은 결과를 이뤄내는 이야기를 담았다.\r [Matilda]는 토니상과 올리비에상을 받은 뮤지컬이 원작이다.",
            "popularity": 348.414,
            "poster_path": "/ga8R3OiOMMgSvZ4cOj8x7prUNYZ.jpg",
            "release_date": "2022-11-25",
            "title": "로알드 달의 뮤지컬 마틸다",
            "video": false,
            "vote_average": 6.9,
            "vote_count": 522
        },
        {
            "adult": false,
            "backdrop_path": "/iXRxlRsBr0mGr9Wx3OPbVdbUJzl.jpg",
            "genre_ids": [
                53,
                27
            ],
            "id": 360784,
            "original_language": "en",
            "original_title": "Hidden",
            "overview": "지상에 퍼진 정체모를 바이러스 때문에 지하에 피신해서 생활하는 가족이야기",
            "popularity": 362.649,
            "poster_path": "/oiNc4aTeaUMVNkxL0UWnezmKJgM.jpg",
            "release_date": "2015-09-15",
            "title": "히든",
            "video": false,
            "vote_average": 6.9,
            "vote_count": 770
        },
        {
            "adult": false,
            "backdrop_path": "/rbUPJoJJquPbX1AiV6GzOqcmJME.jpg",
            "genre_ids": [
                28,
                16,
                35,
                14,
                27,
                10752
            ],
            "id": 587092,
            "original_language": "es",
            "original_title": "Unicorn Wars",
            "overview": "‘러브’ 군사캠프. 테디 베어. 이기적인 블루트와 추하게 늘어진 터비는 조상대대로의 적수인 유니콘과 맞서 싸우기 위해 오늘도 고단한 훈련을 마다하지 않는다. 그들 부대가 유니콘들이 사는 마법의 숲으로 진입하는 순간, 계획은 시작부터 삐걱거리는데...",
            "popularity": 344.865,
            "poster_path": "/joOEYpfltqoqkaiQio24TUTntGM.jpg",
            "release_date": "2022-10-21",
            "title": "유니콘 전쟁",
            "video": false,
            "vote_average": 6.1,
            "vote_count": 26
        }
    ],
    "total_pages": 37470,
    "total_results": 749397
}
